Metadata-Version: 2.4
Name: runpod
Version: 1.7.11
Summary: 🐍 | Python library for RunPod API and serverless worker SDK.
Home-page: https://runpod.io
Author: RunPod
Author-email: RunPod <engineer@runpod.io>, Justin Merrell <justin.merrell@runpod.io>
License: MIT License
Project-URL: Homepage, https://runpod.io
Project-URL: Documentation, https://docs.runpod.io
Project-URL: Repository, https://github.com/runpod/runpod-python
Project-URL: Changelog, https://github.com/runpod/runpod-python/blob/main/CHANGELOG.md
Project-URL: Bug Tracker, https://github.com/runpod/runpod-python/issues
Keywords: runpod,ai,gpu,serverless,SDK,API,python,library
Classifier: Environment :: Web Environment
Classifier: Intended Audience :: Developers
Classifier: License :: OSI Approved :: MIT License
Classifier: Operating System :: OS Independent
Classifier: Programming Language :: Python
Classifier: Programming Language :: Python :: 3
Classifier: Programming Language :: Python :: 3.8
Classifier: Programming Language :: Python :: 3.9
Classifier: Programming Language :: Python :: 3.10
Classifier: Programming Language :: Python :: 3.11
Classifier: Topic :: Internet :: WWW/HTTP
Classifier: Topic :: Internet :: WWW/HTTP :: Dynamic Content
Requires-Python: >=3.8
License-File: LICENSE
Requires-Dist: aiohttp[speedups]>=3.9.3
Requires-Dist: aiohttp-retry>=2.8.3
Requires-Dist: backoff>=2.2.1
Requires-Dist: boto3>=1.26.165
Requires-Dist: click>=8.1.7
Requires-Dist: colorama<0.4.7,>=0.2.5
Requires-Dist: cryptography<46.0.0
Requires-Dist: fastapi[all]>=0.94.0
Requires-Dist: paramiko>=3.3.1
Requires-Dist: prettytable>=3.9.0
Requires-Dist: py-cpuinfo>=9.0.0
Requires-Dist: inquirerpy==0.3.4
Requires-Dist: requests>=2.31.0
Requires-Dist: tomli>=2.0.1
Requires-Dist: tomlkit>=0.12.2
Requires-Dist: tqdm-loggable>=0.1.4
Requires-Dist: urllib3>=1.26.6
Requires-Dist: watchdog>=3.0.0
Provides-Extra: test
Requires-Dist: asynctest; extra == "test"
Requires-Dist: nest_asyncio; extra == "test"
Requires-Dist: faker; extra == "test"
Requires-Dist: pytest-asyncio; extra == "test"
Requires-Dist: pytest-cov; extra == "test"
Requires-Dist: pytest-timeout; extra == "test"
Requires-Dist: pytest-watch; extra == "test"
Requires-Dist: pytest; extra == "test"
Dynamic: author
Dynamic: home-page
Dynamic: license-file
Dynamic: requires-python
